{
  "grade_id": "PC_ABS_CYCOLOY____XCY620S-76701_基础创新塑料_南沙_",
  "grade_name": "PC/ABS CYCOLOY™   XCY620S-76701 基础创新塑料(南沙)",
  "polymer": "ABS",
  "supplier": "Unknown",
  "sources": [
    "https://www.plasway.com/datasheet/detail/DE60EA6AF26A19DDAC8DF6A945BABB7A"
  ],
  "data_source": "plasway_bulk",
  "processing": {},
  "mechanical": {},
  "thermal": {},
  "rheology": {},
  "raw_text": "PC/ABS CYCOLOY™   XCY620S-76701 基础创新塑料(南沙)物性表_性能参数与原料技术参数_TDS 下载_普拉司网（塑料网） 普拉司网 您好，请登录 免费注册 网站地图 塑胶原料 改性新材料 再生塑料 塑料助剂 色母粒 呆滞塑料 塑料机械 企业资讯 行业博文 行业数据 招聘/出租 公共服务 物性认证 品名: 0 种 制造商: 0 家 型号: 0 条 搜索 热门搜索： ABS-台湾奇美 ABS-宁波台化 PC-韩国锦湖 HIPS-镇江奇美 PBT-嘉兴帝人 PA66-河南神马尼龙 精确搜索 分享 下载PDF 加入比对 完善物性 您所在的位置： 首页 物性认证 PC/ABS PC/ABS CYCOLOY™   XCY620S-76701 基础创新塑料(南沙) 253 PC/ABS CYCOLOY™   XCY620S-76701 基础创新塑料(南沙) 253 参考价： 21,140 元/吨 查看供应(31) 产品描述 物性表 认证信息 替代型号(0) 产品描述 典型应用： 电气应用,家电部件 特性： 耐高温,高流动 物性表 物理性能 测试条件 测试方法 测试结果 测试单位 吸水率 23°C,24hr ISO 62 0.30 % 吸水率 饱和,23°C ISO 62 0.40 % 收缩率 TD：3.20mm Internal Method 0.50-0.70 % 收缩率 MD：3.20mm Internal Method 0.50-0.70 % 熔体体积流动速率 265°C/5.0kg ISO 1133 25.0 cm3/10min 熔体体积流动速率 260°C/5.0kg ISO 1133 20.0 cm3/10min 吸水率 平衡,23°C,50%RH ISO 62 0.13 % 机械性能 测试条件 测试方法 测试结果 测试单位 拉伸模量 - ISO 527-2/1 2200 Mpa 拉伸强度 屈服 ISO 527-2/50 54.0 Mpa 拉伸强度 断裂 ISO 527-2/50 56.0 Mpa 拉伸应变 屈服 ISO 527-2/50 4.5 % 拉伸应变 断裂 ISO 527-2/50 100 % 弯曲模量 50.0mmSpan ASTM D790 2300 Mpa 弯曲模量 - ISO 178 2200 Mpa 弯曲强度 - ISO 178 82.0 Mpa 弯曲强度 Yield,50.0mmSpan ASTM D790 86.0 Mpa 热性能 测试条件 测试方法 测试结果 测试单位 线性热膨胀系数 TD：-40到40°C ASTME831 7E-05 cm/cm/°C 线性热膨胀系数 MD：-40到40°C ASTME831 7E-05 cm/cm/°C 球压硬度 100°C10 IEC 60695-10-2 Pass - 球压硬度 75°C IEC 60695-10-2 Pass - 维卡软化温度 - ISO 306/B120 130 °C 维卡软化温度 - ASTM D15259 129 °C 热变形温度 1.8MPa,Unannealed,64.0mmSpan ISO 75-2/Af 106 °C 热变形温度 1.8MPa,未退火,3.20mm ASTM D648 108 °C 热变形温度 0.45MPa,Unannealed,64.0mmSpan ISO 75-2/Bf 126 °C 热变形温度 0.45MPa,未退火,3.20mm ASTM D648 128 °C 电气性能 测试条件 测试方法 测试结果 测试单位 介电强度 3.20mm,在油中 IEC 60243-1 17 KV/mm 介电强度 1.60mm,在油中 IEC 60243-1 25 KV/mm 介电强度 0.800mm,在油中 IEC 60243-1 39 KV/mm 体积电阻率 - IEC 60093 >1.0E+16 ohms·cm 表面电阻率 - IEC 60093 >1.0E+16 ohms 冲击性能 测试条件 测试方法 测试结果 测试单位 落镖冲击 23°C,TotalEnergy ASTM D3763 55.0 J 落镖冲击 -30°C,TotalEnergy ASTM D3763 65.0 J 悬臂梁缺口冲击强度 23°C ISO 180/1A 55 kJ/m² 悬臂梁缺口冲击强度 -30°C ISO 180/1A 40 kJ/m² 简支梁无缺口冲击强度 23°C ISO 179/1eU NoBreak - 简支梁缺口冲击强度 -30°C ISO 179/1eA 45 kJ/m² 简支梁缺口冲击强度 23°C ISO 179/1eA 60 kJ/m² 【免责声明】 普拉司网尽最大努力确保此数据的准确性，但是普拉司网对这些数据值不承担任何责任，并强烈建议在最终选择材料前，就数据值与材料供应商进行验证。 认证信息 上传认证 暂无认证数据 上传认证 替代型号推荐 暂无替代型号推荐 该产品暂时没有可推荐的替代型号 推荐代理商 更多 > 基础创新塑料(南沙) 代理商：东莞市博鑫塑胶原料有限公司 [PC/ABS] XCY620S-76701 22,000元/吨 基础创新塑料(南沙) 代理商：东莞市樟木头新忠茂塑胶原料经营部 [PC/ABS] XCY620S-76701 23,000元/吨 [PC/ABS] XCY620S-76701 23,000元/吨 关于我们 会员服务 欢迎加盟 咨询投诉与建议 联系我们 Copyright © 2000-2026 All Rights Reserved 深圳市普拉司商务网络有限公司 普拉司网（塑料网） 版权所有 本站网络实名： 普拉司网 ICP备案： 粤B2-20050453号 增值电信业务经营许可证： 粤B2-20201126",
  "dynamic_properties": {
    "General": {
      "吸水率 (23°C,24hr) [%]": "0.30",
      "吸水率 (饱和,23°C) [%]": "0.40",
      "收缩率 (TD：3.20mm) [%]": "0.50-0.70",
      "收缩率 (MD：3.20mm) [%]": "0.50-0.70",
      "熔体体积流动速率 (265°C/5.0kg) [cm3/10min]": "25.0",
      "熔体体积流动速率 (260°C/5.0kg) [cm3/10min]": "20.0",
      "吸水率 (平衡,23°C,50%RH) [%]": "0.13",
      "拉伸模量 [Mpa]": "2200",
      "拉伸强度 (屈服) [Mpa]": "54.0",
      "拉伸强度 (断裂) [Mpa]": "56.0",
      "拉伸应变 (屈服) [%]": "4.5",
      "拉伸应变 (断裂) [%]": "100",
      "弯曲模量 (50.0mmSpan) [Mpa]": "2300",
      "弯曲模量 [Mpa]": "2200",
      "弯曲强度 [Mpa]": "82.0",
      "弯曲强度 (Yield,50.0mmSpan) [Mpa]": "86.0",
      "线性热膨胀系数 (TD：-40到40°C) [cm/cm/°C]": "7E-05",
      "线性热膨胀系数 (MD：-40到40°C) [cm/cm/°C]": "7E-05",
      "球压硬度 (100°C10)": "Pass",
      "球压硬度 (75°C)": "Pass",
      "维卡软化温度 [°C]": "129",
      "热变形温度 (1.8MPa,Unannealed,64.0mmSpan) [°C]": "106",
      "热变形温度 (1.8MPa,未退火,3.20mm) [°C]": "108",
      "热变形温度 (0.45MPa,Unannealed,64.0mmSpan) [°C]": "126",
      "热变形温度 (0.45MPa,未退火,3.20mm) [°C]": "128",
      "介电强度 (3.20mm,在油中) [KV/mm]": "17",
      "介电强度 (1.60mm,在油中) [KV/mm]": "25",
      "介电强度 (0.800mm,在油中) [KV/mm]": "39",
      "体积电阻率 [ohms·cm]": ">1.0E+16",
      "表面电阻率 [ohms]": ">1.0E+16",
      "落镖冲击 (23°C,TotalEnergy) [J]": "55.0",
      "落镖冲击 (-30°C,TotalEnergy) [J]": "65.0",
      "悬臂梁缺口冲击强度 (23°C) [kJ/m²]": "55",
      "悬臂梁缺口冲击强度 (-30°C) [kJ/m²]": "40",
      "简支梁无缺口冲击强度 (23°C)": "NoBreak",
      "简支梁缺口冲击强度 (-30°C) [kJ/m²]": "45",
      "简支梁缺口冲击强度 (23°C) [kJ/m²]": "60"
    }
  }
}