{
  "grade_id": "PEI_ULTEM____1000_基础创新塑料_美国_",
  "grade_name": "PEI ULTEM™   1000 基础创新塑料(美国)",
  "polymer": "Unknown",
  "supplier": "Unknown",
  "sources": [
    "https://www.plasway.com/datasheet/detail/ED5F166FDAC5241323ED5507F59C5BE7"
  ],
  "data_source": "plasway_bulk",
  "processing": {},
  "mechanical": {},
  "thermal": {},
  "rheology": {},
  "raw_text": "PEI ULTEM™   1000 基础创新塑料(美国)物性表_性能参数与原料技术参数_TDS 下载_普拉司网（塑料网） 普拉司网 您好，请登录 免费注册 网站地图 塑胶原料 改性新材料 再生塑料 塑料助剂 色母粒 呆滞塑料 塑料机械 企业资讯 行业博文 行业数据 招聘/出租 公共服务 物性认证 品名: 0 种 制造商: 0 家 型号: 0 条 搜索 热门搜索： ABS-台湾奇美 ABS-宁波台化 PC-韩国锦湖 HIPS-镇江奇美 PBT-嘉兴帝人 PA66-河南神马尼龙 精确搜索 分享 下载PDF 加入比对 完善物性 您所在的位置： 首页 物性认证 PEI PEI ULTEM™   1000 基础创新塑料(美国) 459 PEI ULTEM™   1000 基础创新塑料(美国) 459 参考价： 143,850 元/吨 查看供应(20) 产品描述 物性表 认证信息 替代型号(0) 产品描述 典型应用： 汽车领域,电气领域,电子领域 特性： 玻纤增强,阻燃,增强 等级： 注塑级 物性表 物理性能 测试条件 测试方法 测试结果 测试单位 密度 - ASTM D792 1.27 g/cm³ 熔体质量流动速率 337°C/6.6kg ASTM D1238 9.0 g/10min 收缩率 MD：3.20mm Internal Method 0.50-0.70 % 吸水率 24hr ASTM D570 0.25 % 吸水率 平衡,23°C ASTM D570 1.3 % 机械性能 测试条件 测试方法 测试结果 测试单位 弯曲强度 Yield,100mmSpan ASTM D790 165 Mpa 泊松比 - ASTM D638 0.36 - 泰伯耐磨性 1000Cycles,1000g,CS-17转轮 ASTM D1044 10.0 mg 拉伸模量 - ASTM D638 3590 Mpa 拉伸强度 屈服 ASTM D638 110 Mpa 伸长率 屈服 ASTM D638 7.0 % 伸长率 断裂 ASTM D638 60 % 弯曲模量 100mmSpan ASTM D790 3520 Mpa 热性能 测试条件 测试方法 测试结果 测试单位 热变形温度 0.45MPa,未退火,6.40mm ASTM D648 210 °C 热变形温度 1.8MPa,未退火,6.40mm ASTM D648 201 °C 维卡软化温度 - ASTM D15255 219 °C 线性热膨胀系数 MD：-20to150°C ASTME831 5.6E-05 cm/cm/°C 线性热膨胀系数 TD：-20to150°C ASTME831 5.4E-05 cm/cm/°C 导热系数 - ASTMC177 0.22 W/m/K RTI Elec - UL 746 170 °C RTI Imp - UL 746 170 °C RTI Str - UL 746 170 °C 电气性能 测试条件 测试方法 测试结果 测试单位 热丝引燃 HWI UL 746 PLC 1 - 体积电阻率 - ASTM D257 1E+17 ohms·cm 介电强度 1.60mm,inAir ASTM D149 33 KV/mm 介电强度 1.60mm,在油中 ASTM D149 28 KV/mm 介电强度 3.20mm,在油中 ASTM D149 20 KV/mm 介电常数 100Hz ASTM D150 3.15 - 介电常数 1kHz ASTM D150 3.15 - 耗散因数 100Hz ASTM D150 1.5E-03 - 耗散因数 1kHz ASTM D150 1.2E-03 - 耗散因数 2.45GHz ASTM D150 2.5E-03 - 耐电弧性 - ASTM D495 PLC 5 - 相比漏电起痕指数 CTI UL 746 PLC 4 - 高电弧燃烧指数 HAI UL 746 PLC 3 - 高电压电弧起痕速率 HVTR UL 746 PLC 2 - 硬度 测试条件 测试方法 测试结果 测试单位 洛氏硬度 M级 ASTM D785 109 - 可燃性 测试条件 测试方法 测试结果 测试单位 UL阻燃等级 0.40mm UL 94 V-2 - UL阻燃等级 0.75mm UL 94 V-0 - UL阻燃等级 3.0mm UL 94 5VA - 极限氧指数 - ASTM D2863 47 % NBSSmokeDensity-Flaming,Ds,4min - ASTME662 0.700 - 冲击性能 测试条件 测试方法 测试结果 测试单位 悬臂梁缺口冲击强度 23°C ASTM D256 53 J/m 悬臂梁缺口冲击强度 23°C ASTM D4812 1300 J/m 悬臂梁缺口冲击强度 3.20mm ASTM D256 1300 J/m 落镖冲击 23°C ASTM D3029 36.6 J 【免责声明】 普拉司网尽最大努力确保此数据的准确性，但是普拉司网对这些数据值不承担任何责任，并强烈建议在最终选择材料前，就数据值与材料供应商进行验证。 认证信息 上传认证 UL 替代型号推荐 暂无替代型号推荐 该产品暂时没有可推荐的替代型号 关于我们 会员服务 欢迎加盟 咨询投诉与建议 联系我们 Copyright © 2000-2026 All Rights Reserved 深圳市普拉司商务网络有限公司 普拉司网（塑料网） 版权所有 本站网络实名： 普拉司网 ICP备案： 粤B2-20050453号 增值电信业务经营许可证： 粤B2-20201126",
  "dynamic_properties": {
    "General": {
      "密度 [g/cm³]": "1.27",
      "熔体质量流动速率 (337°C/6.6kg) [g/10min]": "9.0",
      "收缩率 (MD：3.20mm) [%]": "0.50-0.70",
      "吸水率 (24hr) [%]": "0.25",
      "吸水率 (平衡,23°C) [%]": "1.3",
      "弯曲强度 (Yield,100mmSpan) [Mpa]": "165",
      "泊松比": "0.36",
      "泰伯耐磨性 (1000Cycles,1000g,CS-17转轮) [mg]": "10.0",
      "拉伸模量 [Mpa]": "3590",
      "拉伸强度 (屈服) [Mpa]": "110",
      "伸长率 (屈服) [%]": "7.0",
      "伸长率 (断裂) [%]": "60",
      "弯曲模量 (100mmSpan) [Mpa]": "3520",
      "热变形温度 (0.45MPa,未退火,6.40mm) [°C]": "210",
      "热变形温度 (1.8MPa,未退火,6.40mm) [°C]": "201",
      "维卡软化温度 [°C]": "219",
      "线性热膨胀系数 (MD：-20to150°C) [cm/cm/°C]": "5.6E-05",
      "线性热膨胀系数 (TD：-20to150°C) [cm/cm/°C]": "5.4E-05",
      "导热系数 [W/m/K]": "0.22",
      "RTI Elec [°C]": "170",
      "RTI Imp [°C]": "170",
      "RTI Str [°C]": "170",
      "热丝引燃 (HWI)": "PLC 1",
      "体积电阻率 [ohms·cm]": "1E+17",
      "介电强度 (1.60mm,inAir) [KV/mm]": "33",
      "介电强度 (1.60mm,在油中) [KV/mm]": "28",
      "介电强度 (3.20mm,在油中) [KV/mm]": "20",
      "介电常数 (100Hz)": "3.15",
      "介电常数 (1kHz)": "3.15",
      "耗散因数 (100Hz)": "1.5E-03",
      "耗散因数 (1kHz)": "1.2E-03",
      "耗散因数 (2.45GHz)": "2.5E-03",
      "耐电弧性": "PLC 5",
      "相比漏电起痕指数 (CTI)": "PLC 4",
      "高电弧燃烧指数 (HAI)": "PLC 3",
      "高电压电弧起痕速率 (HVTR)": "PLC 2",
      "洛氏硬度 (M级)": "109",
      "UL阻燃等级 (0.40mm)": "V-2",
      "UL阻燃等级 (0.75mm)": "V-0",
      "UL阻燃等级 (3.0mm)": "5VA",
      "极限氧指数 [%]": "47",
      "NBSSmokeDensity-Flaming,Ds,4min": "0.700",
      "悬臂梁缺口冲击强度 (23°C) [J/m]": "1300",
      "悬臂梁缺口冲击强度 (3.20mm) [J/m]": "1300",
      "落镖冲击 (23°C) [J]": "36.6"
    }
  }
}